odoo/addons/stock_picking_filter_lot/README.rst
odoo/addons/stock_picking_filter_lot/__init__.py
odoo/addons/stock_picking_filter_lot/__manifest__.py
odoo/addons/stock_picking_filter_lot/i18n/es.po
odoo/addons/stock_picking_filter_lot/i18n/fr.po
odoo/addons/stock_picking_filter_lot/i18n/it.po
odoo/addons/stock_picking_filter_lot/i18n/nl.po
odoo/addons/stock_picking_filter_lot/i18n/pt_BR.po
odoo/addons/stock_picking_filter_lot/i18n/stock_picking_filter_lot.pot
odoo/addons/stock_picking_filter_lot/i18n/tr.po
odoo/addons/stock_picking_filter_lot/models/__init__.py
odoo/addons/stock_picking_filter_lot/models/stock_lot.py
odoo/addons/stock_picking_filter_lot/readme/CONTRIBUTORS.md
odoo/addons/stock_picking_filter_lot/readme/DESCRIPTION.md
odoo/addons/stock_picking_filter_lot/readme/USAGE.md
odoo/addons/stock_picking_filter_lot/static/description/icon.png
odoo/addons/stock_picking_filter_lot/static/description/index.html
odoo/addons/stock_picking_filter_lot/tests/__init__.py
odoo/addons/stock_picking_filter_lot/tests/test_stock_picking_filter_lot.py
odoo/addons/stock_picking_filter_lot/views/stock_move_line_view.xml
odoo/addons/stock_picking_filter_lot/views/stock_scrap_view.xml
odoo_addon_stock_picking_filter_lot-19.0.1.0.0.2.dist-info/METADATA
odoo_addon_stock_picking_filter_lot-19.0.1.0.0.2.dist-info/WHEEL
odoo_addon_stock_picking_filter_lot-19.0.1.0.0.2.dist-info/top_level.txt
odoo_addon_stock_picking_filter_lot-19.0.1.0.0.2.dist-info/RECORD
